IthoRFT/__init__.py
IthoRFT/const.py
IthoRFT/remote.py
pyithorft-1.0.0.dist-info/METADATA
pyithorft-1.0.0.dist-info/WHEEL
pyithorft-1.0.0.dist-info/licenses/LICENSE
pyithorft-1.0.0.dist-info/RECORD
