Metadata-Version: 2.4
Name: pyIthoRFT
Version: 1.0.0
Summary: A python3 library to emulate an IthoRFT remote
Project-URL: Homepage, https://github.com/GraceGRD/pyIthoRFT
Project-URL: Bug Tracker, https://github.com/GraceGRD/pyIthoRFT/issues
Author-email: GraceGRD <123941606+GraceGRD@users.noreply.github.com>
License-File: LICENSE
Classifier: Intended Audience :: Developers
Classifier: License :: OSI Approved :: MIT License
Classifier: Operating System :: OS Independent
Classifier: Programming Language :: Python
Classifier: Programming Language :: Python :: 3
Classifier: Topic :: Home Automation
Classifier: Topic :: Software Development :: Libraries :: Python Modules
Requires-Python: >=3.10
Requires-Dist: pyserial>=3.5
